README.md
setup.py
image_classification/Earlystopping.py
image_classification/__init__.py
image_classification/dataloader.py
image_classification/example.py
image_classification/lr_finder.py
image_classification/model.py
image_classification/training.py
image_classification/util.py
image_classification.egg-info/PKG-INFO
image_classification.egg-info/SOURCES.txt
image_classification.egg-info/dependency_links.txt
image_classification.egg-info/requires.txt
image_classification.egg-info/top_level.txt